[
  {
    "description": "Learn React",
    "completed": true,
    "color": "red",
    "dueDate": 1528213744759,
    "_id": 0.8517449838861129
  },
  {
    "description": "Learn Redux",
    "completed": false,
    "color": "orange",
    "dueDate": 1528213744759,
    "_id": 0.7985830103571325
  },
  { "description": "Sleep", "completed": true, "color": "yellow", "dueDate": 1528213744759, "_id": 0.7482457823972508 },
  {
    "description": "Have lots of fun.",
    "completed": true,
    "color": "green",
    "dueDate": 1528213744759,
    "_id": 0.6057708422243576
  },
  {
    "description": "Become a really great web developer",
    "completed": false,
    "color": "blue",
    "dueDate": 1528213744759,
    "_id": 0.29483646569546773
  }
]
